myturn_sdk/__init__.py
myturn_sdk/browser.py
myturn_sdk/myturn_authenticator.py
myturn_sdk/myturn_client.py
myturn_sdk/myturn_inventory.py
myturn_sdk/myturn_my_account.py
myturn_sdk/myturn_public_info.py
myturn_sdk/myturn_service_base.py
myturn_sdk/myturn_users.py
myturn_sdk/models/__init__.py
myturn_sdk/models/address_response.py
myturn_sdk/models/inventory_item.py
myturn_sdk/models/inventory_search_request.py
myturn_sdk/models/inventory_search_response.py
myturn_sdk/models/login_result.py
myturn_sdk/models/opening_hours.py
myturn_sdk/models/opening_hours_response.py
myturn_sdk/models/opening_times.py
myturn_sdk/models/response_base.py
myturn_sdk/models/user.py
myturn_sdk/models/user_search_request.py
myturn_sdk/models/user_search_response.py
myturn_sdk-0.1.1.dist-info/LICENSE
myturn_sdk-0.1.1.dist-info/METADATA
myturn_sdk-0.1.1.dist-info/WHEEL
myturn_sdk-0.1.1.dist-info/entry_points.txt
myturn_sdk-0.1.1.dist-info/top_level.txt
myturn_sdk-0.1.1.dist-info/RECORD
